{
  "id": "wodlog_225",
  "fileName": "wodlog_[见习冒险团]「17.00级」紫色禁地挑战202603191819.zip",
  "uploadTime": "2026-03-23T15:33:20.783Z",
  "fileSize": 455420,
  "fileCount": 9,
  "metadata": {
    "hasIndex": true,
    "indexFile": "index.html",
    "allFiles": [
      "4642054/level1.html",
      "4642054/level2.html",
      "4642054/level3.html",
      "4642054/level4.html",
      "4642054/level5.html",
      "4642054/level6.html",
      "4642054/statistics.html",
      "4642054/items.html",
      "index.html"
    ]
  },
  "htmlFiles": [
    "4642054/level1.html",
    "4642054/level2.html",
    "4642054/level3.html",
    "4642054/level4.html",
    "4642054/level5.html",
    "4642054/level6.html",
    "4642054/statistics.html",
    "4642054/items.html",
    "index.html"
  ],
  "uploaderId": "user_atmt3n"
}