{
  "id": "wodlog_16",
  "fileName": "wodlog_[灰鹰小队]「8.80级」克伦切的兽人洞202601051955.zip",
  "uploadTime": "2026-01-18T22:05:58.611Z",
  "fileSize": 126309,
  "fileCount": 7,
  "metadata": {
    "hasIndex": true,
    "indexFile": "index.html",
    "allFiles": [
      "4530161/level1.html",
      "4530161/level2.html",
      "4530161/level3.html",
      "4530161/level4.html",
      "4530161/statistics.html",
      "4530161/items.html",
      "index.html"
    ]
  },
  "htmlFiles": [
    "4530161/level1.html",
    "4530161/level2.html",
    "4530161/level3.html",
    "4530161/level4.html",
    "4530161/statistics.html",
    "4530161/items.html",
    "index.html"
  ],
  "uploaderId": "user_xtgcky"
}