{
  "id": "wodlog_229",
  "fileName": "wodlog_[见习冒险团]「17.75级」沼泽中的巨石阵202603200123.zip",
  "uploadTime": "2026-03-23T15:35:20.675Z",
  "fileSize": 512615,
  "fileCount": 10,
  "metadata": {
    "hasIndex": true,
    "indexFile": "index.html",
    "allFiles": [
      "4642526/level1.html",
      "4642526/level2.html",
      "4642526/level3.html",
      "4642526/level4.html",
      "4642526/level5.html",
      "4642526/level6.html",
      "4642526/level7.html",
      "4642526/statistics.html",
      "4642526/items.html",
      "index.html"
    ]
  },
  "htmlFiles": [
    "4642526/level1.html",
    "4642526/level2.html",
    "4642526/level3.html",
    "4642526/level4.html",
    "4642526/level5.html",
    "4642526/level6.html",
    "4642526/level7.html",
    "4642526/statistics.html",
    "4642526/items.html",
    "index.html"
  ],
  "uploaderId": "user_atmt3n"
}