{
  "id": "wodlog_221",
  "fileName": "wodlog_[努力的活着]「18.08级」发狂的炼金术士挑战202603212230.zip",
  "uploadTime": "2026-03-23T15:30:30.634Z",
  "fileSize": 499205,
  "fileCount": 9,
  "metadata": {
    "hasIndex": true,
    "indexFile": "index.html",
    "allFiles": [
      "4645570/level1.html",
      "4645570/level2.html",
      "4645570/level3.html",
      "4645570/level4.html",
      "4645570/level5.html",
      "4645570/level6.html",
      "4645570/statistics.html",
      "4645570/items.html",
      "index.html"
    ]
  },
  "htmlFiles": [
    "4645570/level1.html",
    "4645570/level2.html",
    "4645570/level3.html",
    "4645570/level4.html",
    "4645570/level5.html",
    "4645570/level6.html",
    "4645570/statistics.html",
    "4645570/items.html",
    "index.html"
  ],
  "uploaderId": "user_atmt3n"
}